low_power/counter_power.v
module counter_pwr_gate(
input wire clk,
input wire reset,
input wire power_on,
output reg [3:0]count
);

always @(posedge clk or posedge reset)begin
	if(reset)
		count <= 0;

	else if (power_on)
		count <= count+1;

end
endmodule

low_power/counter_clk_gate.v
module counter_clk_gate(
input wire clk,
input wire reset,
input wire enable,
output reg [3:0] count
);

always @(posedge clk or posedge reset) begin
	if(reset)
		count <=0;
	else if (enable)
		count <= count+1;

end
endmodule

low_power/counter_baseline.v
module counter_baseline(
input wire clk,
input wire reset,
output reg  [3:0]count
);

always @(posedge clk or posedge reset) begin
	if(reset)
		count <= 0;
	else
		count <= count+1;
end
endmodule

low_power/low_power_tb.v
module low_power_tb;
reg clk = 0;
reg reset =1;
reg enable = 0;
reg power_on = 0;
wire [3:0] count_base, count_clk_gate, count_pwr_gate;

always #5 clk <= ~clk;

counter_baseline u1(
.clk(clk),
.reset(reset),
.count(count_base)
);

counter_clk_gate u2(
.clk(clk),
.reset(reset),
.enable(enable),
.count(count_clk_gate)
);

counter_pwr_gate u3(
.clk(clk),
.reset(reset),
.power_on(power_on),
.count(count_pwr_gate)
);

initial begin
	$dumpfile("dump.vcd");
	$dumpvars(0,low_power_tb);

	#10 reset = 0;

	#10 enable =1;

	#20 power_on = 0;

	#20 enable = 1 ; power_on =1;

	#40 $finish;

end
endmodule

low_power/obj_dir/dump.vcd
$version Generated by VerilatedVcd $end
$timescale 1ps $end

 $scope module TOP $end
  $scope module low_power_tb $end
   $var wire  1 & clk $end
   $var wire  4 # count_base [3:0] $end
   $var wire  4 $ count_clk_gate [3:0] $end
   $var wire  4 % count_pwr_gate [3:0] $end
   $var wire  1 ( enable $end
   $var wire  1 ) power_on $end
   $var wire  1 ' reset $end
   $scope module u1 $end
    $var wire  1 & clk $end
    $var wire  4 # count [3:0] $end
    $var wire  1 ' reset $end
   $upscope $end
   $scope module u2 $end
    $var wire  1 & clk $end
    $var wire  4 $ count [3:0] $end
    $var wire  1 ( enable $end
    $var wire  1 ' reset $end
   $upscope $end
   $scope module u3 $end
    $var wire  1 & clk $end
    $var wire  4 % count [3:0] $end
    $var wire  1 ) power_on $end
    $var wire  1 ' reset $end
   $upscope $end
  $upscope $end
 $upscope $end
$enddefinitions $end


#0
b0000 #
b0000 $
b0000 %
0&
1'
0(
0)
#5
1&
#10
0&
0'
#15
b0001 #
1&
#20
0&
1(
#25
b0010 #
b0001 $
1&
#30
0&
#35
b0011 #
b0010 $
1&
#40
0&
#45
b0100 #
b0011 $
1&
#50
0&
#55
b0101 #
b0100 $
1&
#60
0&
1)
#65
b0110 #
b0101 $
b0001 %
1&
#70
0&
#75
b0111 #
b0110 $
b0010 %
1&
#80
0&
#85
b1000 #
b0111 $
b0011 %
1&
#90
0&
#95
b1001 #
b1000 $
b0100 %
1&
